things_mcp/__init__.py
things_mcp/config.py
things_mcp/fast_server.py
things_mcp/formatters.py
things_mcp/handlers.py
things_mcp/mcp_tools.py
things_mcp/things_server.py
things_mcp/url_scheme.py
things_mcp/utils.py
mseep_things_fastmcp-1.0.2.dist-info/METADATA
mseep_things_fastmcp-1.0.2.dist-info/WHEEL
mseep_things_fastmcp-1.0.2.dist-info/entry_points.txt
mseep_things_fastmcp-1.0.2.dist-info/RECORD
